dbce.py
dbce-0.1.1.dist-info/WHEEL
dbce-0.1.1.dist-info/METADATA
dbce-0.1.1.dist-info/RECORD
