Metadata-Version: 2.1
Name: dbce
Version: 0.1.1
Summary: DBCE - Discord Bot Creator Easy to use library for creating discord bots
Author: peaky
Author-email: nerfinyt@gmail.com
Requires-Python: >=3.6,<4.0
Classifier: Programming Language :: Python :: 3
Classifier: Programming Language :: Python :: 3.10
Classifier: Programming Language :: Python :: 3.6
Classifier: Programming Language :: Python :: 3.7
Classifier: Programming Language :: Python :: 3.8
Classifier: Programming Language :: Python :: 3.9
